AnquanKe2020q2/README.md
AnquanKe2020q2/__init__.py
AnquanKe2020q2/__main__.py
AnquanKe2020q2/file.epub
AnquanKe2020q2/index.html
AnquanKe2020q2/css/__init__.py
AnquanKe2020q2/css/annotations.css
AnquanKe2020q2/css/main.css
AnquanKe2020q2/css/normalize.css
AnquanKe2020q2/css/popup.css
AnquanKe2020q2/font/__init__.py
AnquanKe2020q2/font/fontello.eot
AnquanKe2020q2/font/fontello.svg
AnquanKe2020q2/font/fontello.ttf
AnquanKe2020q2/font/fontello.woff
AnquanKe2020q2/img/__init__.py
AnquanKe2020q2/img/annotator-glyph-sprite.png
AnquanKe2020q2/img/annotator-icon-sprite.png
AnquanKe2020q2/img/apple-touch-icon.png
AnquanKe2020q2/img/cancelfullscreen.png
AnquanKe2020q2/img/close.png
AnquanKe2020q2/img/fullscreen.png
AnquanKe2020q2/img/loader.gif
AnquanKe2020q2/img/menu-icon.png
AnquanKe2020q2/img/save.png
AnquanKe2020q2/img/saved.png
AnquanKe2020q2/img/settings-s.png
AnquanKe2020q2/img/settings.png
AnquanKe2020q2/img/star.png
AnquanKe2020q2/js/__init__.py
AnquanKe2020q2/js/epub.js
AnquanKe2020q2/js/epub.min.js
AnquanKe2020q2/js/epub.min.map
AnquanKe2020q2/js/hooks.min.js
AnquanKe2020q2/js/hooks.min.map
AnquanKe2020q2/js/reader.js
AnquanKe2020q2/js/reader.js.map
AnquanKe2020q2/js/reader.min.js
AnquanKe2020q2/js/reader.min.map
AnquanKe2020q2/js/hooks/__init__.py
AnquanKe2020q2/js/hooks/extensions/__init__.py
AnquanKe2020q2/js/hooks/extensions/highlight.js
AnquanKe2020q2/js/libs/__init__.py
AnquanKe2020q2/js/libs/jquery.min.js
AnquanKe2020q2/js/libs/localforage.min.js
AnquanKe2020q2/js/libs/screenfull.js
AnquanKe2020q2/js/libs/screenfull.min.js
AnquanKe2020q2/js/libs/zip.min.js
AnquanKe2020q2/js/plugins/__init__.py
AnquanKe2020q2/js/plugins/hypothesis.js
AnquanKe2020q2/js/plugins/search.js
anquan_ke_2020q2-2024.3.6.0.dist-info/METADATA
anquan_ke_2020q2-2024.3.6.0.dist-info/WHEEL
anquan_ke_2020q2-2024.3.6.0.dist-info/entry_points.txt
anquan_ke_2020q2-2024.3.6.0.dist-info/top_level.txt
anquan_ke_2020q2-2024.3.6.0.dist-info/RECORD
